showtime/__init__.py
showtime/__main__.py
showtime/cli.py
showtime/core/__init__.py
showtime/core/aws.py
showtime/core/constants.py
showtime/core/date_utils.py
showtime/core/emojis.py
showtime/core/git_validation.py
showtime/core/github.py
showtime/core/github_messages.py
showtime/core/label_colors.py
showtime/core/pull_request.py
showtime/core/service_name.py
showtime/core/show.py
showtime/core/sync_state.py
showtime/data/ecs-task-definition.json
superset_showtime-0.6.9.dist-info/METADATA
superset_showtime-0.6.9.dist-info/WHEEL
superset_showtime-0.6.9.dist-info/entry_points.txt
superset_showtime-0.6.9.dist-info/RECORD
