Metadata-Version: 2.4
Name: superset-showtime
Version: 0.6.9
Summary: 🎪 Apache Superset ephemeral environment management with circus tent emoji state tracking
Project-URL: Homepage, https://github.com/apache/superset-showtime
Project-URL: Documentation, https://superset-showtime.readthedocs.io/
Project-URL: Repository, https://github.com/apache/superset-showtime.git
Project-URL: Bug Tracker, https://github.com/apache/superset-showtime/issues
Project-URL: Changelog, https://github.com/apache/superset-showtime/blob/main/CHANGELOG.md
Author-email: Maxime Beauchemin <maximebeauchemin@gmail.com>
License-Expression: Apache-2.0
Keywords: aws,circus,devops,environments,ephemeral,github,showtime,superset
Classifier: Development Status :: 4 - Beta
Classifier: Environment :: Console
Classifier: Intended Audience :: Developers
Classifier: License :: OSI Approved :: Apache Software License
Classifier: Operating System :: OS Independent
Classifier: Programming Language :: Python
Classifier: Programming Language :: Python :: 3
Classifier: Programming Language :: Python :: 3.8
Classifier: Programming Language :: Python :: 3.9
Classifier: Programming Language :: Python :: 3.10
Classifier: Programming Language :: Python :: 3.11
Classifier: Programming Language :: Python :: 3.12
Classifier: Topic :: Software Development :: Build Tools
Classifier: Topic :: System :: Systems Administration
Requires-Python: >=3.8
Requires-Dist: boto3>=1.26.0
Requires-Dist: botocore>=1.29.0
Requires-Dist: gitpython>=3.1.0
Requires-Dist: httpx>=0.24.0
Requires-Dist: pydantic>=2.0.0
Requires-Dist: python-dateutil>=2.8.0
Requires-Dist: pyyaml>=6.0
Requires-Dist: rich>=10.0.0
Requires-Dist: typer>=0.9.0
Provides-Extra: all
Requires-Dist: azure-mgmt-containerinstance>=10.0.0; extra == 'all'
Requires-Dist: azure-storage-blob>=12.0.0; extra == 'all'
Requires-Dist: boto3>=1.26.0; extra == 'all'
Requires-Dist: botocore>=1.29.0; extra == 'all'
Requires-Dist: google-cloud-compute>=1.11.0; extra == 'all'
Requires-Dist: google-cloud-storage>=2.8.0; extra == 'all'
Requires-Dist: kubernetes>=26.0.0; extra == 'all'
Provides-Extra: aws
Requires-Dist: boto3>=1.26.0; extra == 'aws'
Requires-Dist: botocore>=1.29.0; extra == 'aws'
Provides-Extra: azure
Requires-Dist: azure-mgmt-containerinstance>=10.0.0; extra == 'azure'
Requires-Dist: azure-storage-blob>=12.0.0; extra == 'azure'
Provides-Extra: dev
Requires-Dist: boto3-stubs[ec2,ecr,ecs]>=1.40.0; extra == 'dev'
Requires-Dist: build>=1.0.0; extra == 'dev'
Requires-Dist: mypy>=1.0.0; extra == 'dev'
Requires-Dist: pre-commit>=3.0.0; extra == 'dev'
Requires-Dist: pytest-cov>=4.0.0; extra == 'dev'
Requires-Dist: pytest>=7.0.0; extra == 'dev'
Requires-Dist: ruff>=0.1.9; extra == 'dev'
Requires-Dist: twine>=4.0.0; extra == 'dev'
Provides-Extra: gcp
Requires-Dist: google-cloud-compute>=1.11.0; extra == 'gcp'
Requires-Dist: google-cloud-storage>=2.8.0; extra == 'gcp'
Provides-Extra: k8s
Requires-Dist: kubernetes>=26.0.0; extra == 'k8s'
